nonebot_plugin_amitabha/__init__.py
nonebot_plugin_amitabha/config.py
nonebot_plugin_amitabha/exception.py
nonebot_plugin_amitabha/util.py
nonebot_plugin_amitabha-0.1.5.dist-info/LICENSE
nonebot_plugin_amitabha-0.1.5.dist-info/METADATA
nonebot_plugin_amitabha-0.1.5.dist-info/WHEEL
nonebot_plugin_amitabha-0.1.5.dist-info/top_level.txt
nonebot_plugin_amitabha-0.1.5.dist-info/RECORD
