Metadata-Version: 2.1
Name: nonebot-plugin-amitabha
Version: 0.1.5
Summary: 基于nonebot2的群聊赛博念佛插件
Author-email: kaguya233qwq <1435608435@qq.com>
License: MIT
Requires-Python: >=3.9
License-File: LICENSE
Requires-Dist: nonebot2>=2.4.0
Requires-Dist: httpx>=0.28.1
Requires-Dist: nonebot-adapter-onebot>=2.4.6
Requires-Dist: nonebot-plugin-localstore>=0.7.2
